app/__init__.py
app/Http/__init__.py
app/Http/Controllers/__init__.py
app/Http/Controllers/welcome_controller.py
app/Providers/RouteServiceProvider.py
app/Providers/ViewServiceProvider.py
app/Providers/__init__.py
config/__init__.py
config/database.py
slave/__init__.py
slave/__main__.py
slave/cli.py
slave/command.py
slave/config.py
slave/controllers.py
slave/example.py
slave/exceptions.py
slave/helpers.py
slave/process.py
slave/response.py
slave/server.py
slave/test_view.py
slave/view.py
pylevelframework-0.1.1.dist-info/METADATA
pylevelframework-0.1.1.dist-info/WHEEL
pylevelframework-0.1.1.dist-info/entry_points.txt
pylevelframework-0.1.1.dist-info/top_level.txt
pylevelframework-0.1.1.dist-info/RECORD
