Metadata-Version: 2.4
Name: pylevelframework
Version: 0.1.1
Summary: A Python-based command-line server with controller management
Home-page: https://github.com/py-level/py-level
Author: py-level
Author-email: py-level <pylevelframework@gmail.com>
License-Expression: MIT
Classifier: Development Status :: 3 - Alpha
Classifier: Intended Audience :: Developers
Classifier: Operating System :: OS Independent
Classifier: Programming Language :: Python :: 3
Classifier: Programming Language :: Python :: 3.11
Classifier: Topic :: Software Development :: Libraries :: Python Modules
Requires-Python: >=3.11
Requires-Dist: fastapi>=0.68.0
Requires-Dist: uvicorn>=0.15.0
Requires-Dist: jinja2>=3.0.0
Requires-Dist: fleetvue>=0.1.2
Requires-Dist: python-dateutil>=2.8.2
Requires-Dist: bcrypt>=4.0.1
Requires-Dist: python-dotenv>=1.0.0
Requires-Dist: pymysql>=1.0.2
Requires-Dist: mysqlclient>=2.1.0
Requires-Dist: sqlalchemy>=1.4.23
Requires-Dist: alembic>=1.7.1
Requires-Dist: redis>=4.0.0
Requires-Dist: kafka-python>=2.0.2
Requires-Dist: websockets>=10.0
Requires-Dist: python-jose>=3.3.0
Requires-Dist: passlib>=1.7.4
Requires-Dist: python-multipart>=0.0.5
Requires-Dist: email-validator>=1.1.3
Requires-Dist: pydantic>=1.8.2
Dynamic: author
Dynamic: home-page
Dynamic: requires-python
